stk_widgets/__init__.py
stk_widgets/widgets/__init__.py
stk_widgets/widgets/buttons.py
stk_widgets/widgets/chat_bubble.py
stk_widgets/widgets/effects.py
stk_widgets/widgets/entries.py
stk_widgets/widgets/labels.py
stk_widgets/widgets/popups.py
stk_widgets/widgets/spinner.py
stk_widgets/widgets/tabs.py
stk_widgets/widgets/verticaltabs.py
stk_widgets/window/__init__.py
stk_widgets/window/filedialog.py
stk_widgets/window/layouts.py
stk_widgets/window/menubar.py
stk_widgets/window/stkmessagebox.py
stk_widgets/window/stylable_window.py
stk_widgets/window/icons/app.png
stk_widgets/window/icons/archive.png
stk_widgets/window/icons/audio.png
stk_widgets/window/icons/code.png
stk_widgets/window/icons/error.png
stk_widgets/window/icons/folder.png
stk_widgets/window/icons/gif.png
stk_widgets/window/icons/image.png
stk_widgets/window/icons/info.png
stk_widgets/window/icons/open.png
stk_widgets/window/icons/option.png
stk_widgets/window/icons/pdf.png
stk_widgets/window/icons/python.png
stk_widgets/window/icons/question.png
stk_widgets/window/icons/text.png
stk_widgets/window/icons/unknown.png
stk_widgets/window/icons/video.png
stk_widgets/window/icons/warning.png
stk_widgets-0.1.3.dist-info/licenses/LICENSE
stk_widgets-0.1.3.dist-info/METADATA
stk_widgets-0.1.3.dist-info/WHEEL
stk_widgets-0.1.3.dist-info/top_level.txt
stk_widgets-0.1.3.dist-info/RECORD
