Metadata-Version: 2.4
Name: stk_widgets
Version: 0.1.3
Summary: Custom widgets for tkinter
Author: Oladapo Akintola
License-Expression: MIT
Project-URL: Homepage, https://github.com/OladapoAkintola/stk-widgets
Keywords: tkinter,widgets,GUI
Classifier: Programming Language :: Python :: 3
Classifier: Operating System :: OS Independent
Requires-Python: >=3.9
License-File: LICENSE
Requires-Dist: customtkinter
Requires-Dist: Pillow
Requires-Dist: hPyT
Requires-Dist: rich
Dynamic: license-file
